hexa/__init__.py
hexa-0.0.3.dist-info/METADATA
hexa-0.0.3.dist-info/WHEEL
hexa-0.0.3.dist-info/top_level.txt
hexa-0.0.3.dist-info/RECORD
