Metadata-Version: 2.1
Name: hexa
Version: 0.0.3
Summary: Hexagonal Architecture with Domain Driven Design
Author-email: Andrew Dunai <a@dun.ai>
Project-URL: Homepage, https://github.com/and3rson/hexa
Classifier: Programming Language :: Python :: 3
Classifier: License :: OSI Approved :: MIT License
Classifier: Operating System :: OS Independent
Requires-Python: >=3.7
Requires-Dist: pydantic (==1.10.4)
